{
  "uuid": "ecf3abb9-e1b6-45fc-a67c-fba37c922771",
  "first_name": "Joseph",
  "last_name": "Cohen, M.D., F.A.A.P.",
  "full_name": "Joseph Cohen, M.D., F.A.A.P.",
  "linkedin_url": "https://linkedin.com/in/joseph-cohen-m-d-f-a-a-p-8272036",
  "emails": [
    {
      "email": "drjoe@cedar-park-pediatrics.com",
      "type": "Work",
      "status": "Unverifiable"
    },
    {
      "email": "joseph.cohen@hootsuite.com",
      "type": "Work",
      "status": "Unverifiable"
    },
    {
      "email": "joseph.cohen@stdavids.com",
      "type": "Work",
      "status": "Unverifiable"
    }
  ],
  "phones": [
    {
      "phone": "+1 604-681-4668",
      "type": "Work",
      "country_code": "US",
      "is_valid": true
    }
  ],
  "organization_name": "The University of Texas Medical Branch at Galveston"
}