{
  "uuid": "9e3db352-1624-43c0-ac38-2b9405a56880",
  "first_name": "Narinder",
  "last_name": "Singh",
  "full_name": "Narinder Singh",
  "linkedin_url": "https://linkedin.com/in/narinder",
  "emails": [
    {
      "email": "linkedin@narinder.com",
      "type": "Work",
      "status": "Unverifiable"
    },
    {
      "email": "narinder@appirio.com",
      "type": "Work",
      "status": "Unverifiable"
    },
    {
      "email": "narinder.singh@softwareag.com",
      "type": "Work",
      "status": "Unverifiable"
    },
    {
      "email": "narinder.singh@partech.com",
      "type": "Work",
      "status": "Unverifiable"
    }
  ],
  "phones": [],
  "organization_name": "LookDeep Health"
}